[
  {
    "id": 1751713072002,
    "user": "usuario1",
    "fecha": "2025-07-10",
    "mensaje": "dia fértil 10"
  },
  {
    "id": 1751713290976,
    "user": "usuario1",
    "fecha": "2025-07-02",
    "mensaje": "dia fértil 2"
  },
  {
    "id": 1751713432313,
    "user": "usuario1",
    "fecha": "2025-07-04",
    "mensaje": "recordar"
  },
  {
    "id": 1751713680294,
    "user": "usuario1",
    "fecha": "2025-07-18",
    "mensaje": "fecha imp"
  },
  {
    "id": 1751713705379,
    "user": "usuario1",
    "fecha": "2025-07-12",
    "mensaje": "ok"
  },
  {
    "id": 1751713871679,
    "user": "usuario1",
    "fecha": "2025-07-05",
    "mensaje": "lo hice"
  },
  {
    "id": 1751714480100,
    "user": "usuario1",
    "fecha": "2025-07-12",
    "mensaje": "a"
  },
  {
    "id": 1751715011192,
    "user": "usuario1",
    "fecha": "2025-07-19",
    "mensaje": "jaajajaj"
  },
  {
    "id": 1751715015359,
    "user": "usuario1",
    "fecha": "2025-07-11",
    "mensaje": "jaajaaajajaajj"
  }
]